README.rst
setup.py
django_swiftstorage.egg-info/PKG-INFO
django_swiftstorage.egg-info/SOURCES.txt
django_swiftstorage.egg-info/dependency_links.txt
django_swiftstorage.egg-info/top_level.txt
swiftstorage/__init__.py
swiftstorage/models.py
swiftstorage/settings.py
swiftstorage/storage.py
swiftstorage/tests.py