Metadata-Version: 1.1
Name: django-swiftstorage
Version: 1.1.0
Summary: Django swiftstorage for Swift API
Home-page: http://launchpad.net/django-swiftstorage/
Author: David Murphy
Author-email: david.murphy@canonical.com
License: UNKNOWN
Platform: UNKNOWN
Classifier: Development Status :: 5 - Production/Stable
Classifier: Framework :: Django
Classifier: Intended Audience :: Developers
Classifier: License :: OSI Approved :: GNU Lesser General Public License v3 (LGPLv3)
Classifier: Programming Language :: Python :: 2.7
